svalbard/__init__.py
svalbard-0.2.1.dist-info/LICENSE
svalbard-0.2.1.dist-info/METADATA
svalbard-0.2.1.dist-info/WHEEL
svalbard-0.2.1.dist-info/top_level.txt
svalbard-0.2.1.dist-info/RECORD
