Metadata-Version: 2.1
Name: svalbard
Version: 0.2.1
Summary: Easy time handling in the context of weather forecasting
Home-page: http://github.com/paulskeie/svalbard
Author: Paul Skeie
Author-email: paul.skeie@gmail.com
License: Apache-2.0
Platform: UNKNOWN
Requires-Dist: requests
